LICENSE
README.md
setup.py
janni/__init__.py
janni/jmain.py
janni/models.py
janni/patch_pair_generator.py
janni/predict.py
janni/train.py
janni/utils.py
janni.egg-info/PKG-INFO
janni.egg-info/SOURCES.txt
janni.egg-info/dependency_links.txt
janni.egg-info/entry_points.txt
janni.egg-info/requires.txt
janni.egg-info/top_level.txt