Metadata-Version: 2.1
Name: janni
Version: 0.3.1
Summary: noise 2 noise for cryo em data
Home-page: https://github.com/MPI-Dortmund/sphire-janni
Author: Thorsten Wagner
Author-email: thorsten.wagner@mpi-dortmund.mpg.de
License: MIT
Requires-Python: >=3.5.0, <3.9
Provides-Extra: gpu
Provides-Extra: cpu
License-File: LICENSE
